{
  "word": "lighttpd",
  "ipa": "/ˈlaɪti/",
  "respelling_us": "lie tee",
  "alt_ipa": [],
  "alt_respelling_us": [],
  "source_url": "https://www.lighttpd.net/",
  "source_label": "lighttpd.net — official site (pronounced /lighty/)",
  "category": "product",
  "confidence": "creator-clarified",
  "notes": "Portmanteau of light + httpd; the official site states it is pronounced \"lighty\".",
  "audio_url": "https://pronounce.renlab.ai/audio/lighttpd.mp3",
  "url": "https://pronounce.renlab.ai/word/lighttpd",
  "date_modified": "2026-07-17"
}
