{
  "word": "seedream",
  "ipa": "/ˈsiːdriːm/",
  "respelling_us": "seed reem",
  "alt_ipa": [],
  "alt_respelling_us": [],
  "source_url": "https://seed.bytedance.com/en/seedream4_5",
  "source_label": "ByteDance Seed — Seedream 4.5 official page",
  "category": "product",
  "confidence": "community-consensus",
  "notes": "ByteDance Seed's text-to-image model (Seedream 4.0/4.5, 2025-2026; 4K). Portmanteau of Seed + dream, parallel to siblings Seedance (Seed+dance, video) and SeedEdit — so SEED-reem, not see-DREEM. STRESS: SEED-reem (primary stress on first syllable). The Seed prefix is ByteDance's research division.",
  "audio_url": "https://pronounce.renlab.ai/audio/seedream.mp3",
  "url": "https://pronounce.renlab.ai/word/seedream",
  "date_modified": "2026-06-16"
}
