{
  "word": "SQLite",
  "ipa": "/ňĆ…õs kjuňź …õl ňąa…™t/",
  "respelling_us": "S Q L ite",
  "alt_ipa": ["/ňąsiňźkw…ôl la…™t/"],
  "alt_respelling_us": ["sequel ite"],
  "source_url": "https://www.sqlite.org/famous.html",
  "source_label": "SQLite docs",
  "category": "product",
  "confidence": "community-consensus",
  "notes": "\"S-Q-L-ite\" preferred (per project lore).",
  "audio_url": "https://pronounce.renlab.ai/audio/sqlite.mp3",
  "url": "https://pronounce.renlab.ai/word/sqlite",
  "date_modified": "2026-07-12"
}
