{
  "word": "watchexec",
  "ipa": "/ˈwɒtʃ.ɛɡˌzɛk/",
  "respelling_us": "wotch eg zek",
  "alt_ipa": [],
  "alt_respelling_us": [],
  "source_url": "https://github.com/watchexec/watchexec",
  "source_label": "watchexec/watchexec — GitHub (official repo)",
  "category": "cli-tool",
  "confidence": "community-consensus",
  "notes": "Cross-platform Rust file-watcher that runs a command on file changes (alternative to entr/nodemon). Name = \"watch\" + \"exec\" (execute). The \"exec\" suffix follows dev-tooling convention (cf. the exec syscall / shell builtin): \"eg-ZEK\", not \"ex-eck\". STRESS: WOTCH-eg-zek (primary on first syllable, secondary on -ZEK). No official creator pronunciation FAQ exists, but the compound is unambiguous.",
  "audio_url": "https://pronounce.renlab.ai/audio/watchexec.mp3",
  "url": "https://pronounce.renlab.ai/word/watchexec",
  "date_modified": "2026-06-24"
}
